fancybox/__init__.py
fancybox/__main__.py
fancybox/box.py
fancybox/line.py
fancybox/message.py
fancybox/style.py
fancybox/style_bk.py
fancybox/textprocessor.py
fancybox-1.0.0.dist-info/LICENSE
fancybox-1.0.0.dist-info/METADATA
fancybox-1.0.0.dist-info/WHEEL
fancybox-1.0.0.dist-info/top_level.txt
fancybox-1.0.0.dist-info/RECORD
