Metadata-Version: 2.1
Name: fancybox
Version: 1.0.0
Summary: Print beautiful message boxes on command line
Home-page: https://github.com/shivampip/FancyBox
Author: Shivam Agrawal
Author-email: shivam301296@gmail.com
License: UNKNOWN
Platform: UNKNOWN
Classifier: Programming Language :: Python :: 3
Classifier: License :: OSI Approved :: MIT License
Classifier: Operating System :: OS Independent
